simplex_assimilate/__init__.py
simplex_assimilate/_dirichlet.py
simplex_assimilate/cdf.py
simplex_assimilate/dirichlet/__init__.py
simplex_assimilate/dirichlet/dirichlet.py
simplex_assimilate/dirichlet/simplex.py
simplex_assimilate/fixed_point.py
simplex_assimilate/simple_class_transport.py
simplex_assimilate/t.ipynb
simplex_assimilate/transport.py
simplex_assimilate/utils/__init__.py
simplex_assimilate/utils/quantize.py
simplex_assimilate-0.2.10.dist-info/METADATA
simplex_assimilate-0.2.10.dist-info/WHEEL
simplex_assimilate-0.2.10.dist-info/RECORD
