Metadata-Version: 2.1
Name: simplex-assimilate
Version: 0.2.10
Summary: Perform Data Assimilation on the Simplex. Models an ensemble as a mixture of Dirichlet distributions.
Author: Oscar Laird
Author-email: olaird25@gmail.com
Requires-Python: >=3.11,<3.12
Classifier: Programming Language :: Python :: 3
Classifier: Programming Language :: Python :: 3.11
Requires-Dist: graphviz (>=0.20.1,<0.21.0)
Requires-Dist: ipykernel (>=6.29.0,<7.0.0)
Requires-Dist: numpy (>=1.24.3,<2.0.0)
Requires-Dist: scipy (>=1.10.1,<2.0.0)
